allauth_adfs/__init__.py
allauth_adfs/models.py
allauth_adfs/socialaccount/__init__.py
allauth_adfs/socialaccount/adapter.py
allauth_adfs/socialaccount/providers/__init__.py
allauth_adfs/socialaccount/providers/adfs_oauth2/__init__.py
allauth_adfs/socialaccount/providers/adfs_oauth2/compat.py
allauth_adfs/socialaccount/providers/adfs_oauth2/provider.py
allauth_adfs/socialaccount/providers/adfs_oauth2/tests.py
allauth_adfs/socialaccount/providers/adfs_oauth2/urls.py
allauth_adfs/socialaccount/providers/adfs_oauth2/utils.py
allauth_adfs/socialaccount/providers/adfs_oauth2/views.py
django_allauth_adfs-0.1.5.dist-info/DESCRIPTION.rst
django_allauth_adfs-0.1.5.dist-info/METADATA
django_allauth_adfs-0.1.5.dist-info/RECORD
django_allauth_adfs-0.1.5.dist-info/WHEEL
django_allauth_adfs-0.1.5.dist-info/metadata.json
django_allauth_adfs-0.1.5.dist-info/pbr.json
django_allauth_adfs-0.1.5.dist-info/top_level.txt
